aetherpost_source/__init__.py
aetherpost_source/__main__.py
aetherpost_source/cli/__init__.py
aetherpost_source/cli/banner.py
aetherpost_source/cli/commands/__init__.py
aetherpost_source/cli/commands/apply.py
aetherpost_source/cli/commands/auth.py
aetherpost_source/cli/commands/destroy.py
aetherpost_source/cli/commands/doctor.py
aetherpost_source/cli/commands/helper.py
aetherpost_source/cli/commands/init.py
aetherpost_source/cli/commands/plan.py
aetherpost_source/cli/commands/profile.py
aetherpost_source/cli/commands/scheduler.py
aetherpost_source/cli/commands/setup.py
aetherpost_source/cli/common/base_command.py
aetherpost_source/cli/framework/__init__.py
aetherpost_source/cli/framework/command_factory.py
aetherpost_source/cli/framework/response_formatter.py
aetherpost_source/cli/main.py
aetherpost_source/cli/utils/ui.py
aetherpost_source/core/__init__.py
aetherpost_source/core/analytics/__init__.py
aetherpost_source/core/analytics/dashboard.py
aetherpost_source/core/analytics/realtime.py
aetherpost_source/core/cache/__init__.py
aetherpost_source/core/campaigns/templates.py
aetherpost_source/core/common/base_models.py
aetherpost_source/core/common/config_manager.py
aetherpost_source/core/common/error_handler.py
aetherpost_source/core/common/template_engine.py
aetherpost_source/core/common/utils.py
aetherpost_source/core/config/__init__.py
aetherpost_source/core/config/models.py
aetherpost_source/core/config/parser.py
aetherpost_source/core/config/reddit.py
aetherpost_source/core/config/unified.py
aetherpost_source/core/config/validation_engine.py
aetherpost_source/core/config/youtube.py
aetherpost_source/core/content/__init__.py
aetherpost_source/core/content/generator.py
aetherpost_source/core/content/strategy.py
aetherpost_source/core/context/__init__.py
aetherpost_source/core/context/diff_detector.py
aetherpost_source/core/context/project_reader.py
aetherpost_source/core/detection/__init__.py
aetherpost_source/core/detection/git_detector.py
aetherpost-1.11.1.dist-info/LICENSE
aetherpost-1.11.1.dist-info/METADATA
aetherpost-1.11.1.dist-info/WHEEL
aetherpost-1.11.1.dist-info/entry_points.txt
aetherpost-1.11.1.dist-info/RECORD
