Metadata-Version: 2.3
Name: aetherpost
Version: 1.11.1
Summary: Promotion as Code - Automate your app promotion across social media platforms
Author: AetherPost Team
Author-email: team@aetherpost.dev
Requires-Python: >=3.10,<4.0
Classifier: Programming Language :: Python :: 3
Classifier: Programming Language :: Python :: 3.10
Classifier: Programming Language :: Python :: 3.11
Classifier: Programming Language :: Python :: 3.12
Classifier: Programming Language :: Python :: 3.13
Requires-Dist: PyYAML (>=6.0,<7.0)
Requires-Dist: aiohttp (>=3.10.0,<4.0.0)
Requires-Dist: anthropic (>=0.25.0,<0.26.0)
Requires-Dist: asyncio-throttle (>=1.0.0,<2.0.0)
Requires-Dist: click (>=8.0.0,<9.0.0)
Requires-Dist: cryptography (>=41.0.0,<42.0.0)
Requires-Dist: fastapi (>=0.100.0,<0.101.0)
Requires-Dist: openai (>=1.52.0,<2.0.0)
Requires-Dist: pillow (>=10.0.0,<11.0.0)
Requires-Dist: pydantic (>=2.11.0,<3.0.0)
Requires-Dist: python-dotenv (>=1.0.0,<2.0.0)
Requires-Dist: requests (>=2.32.0,<3.0.0)
Requires-Dist: rich (>=13.0.0,<14.0.0)
Requires-Dist: tweepy (>=4.14.0,<5.0.0)
Requires-Dist: typer (>=0.9.0,<0.10.0)
